parallelexec/__init__.py
parallelexec/py.typed
parallelexec-0.0.3.dist-info/METADATA
parallelexec-0.0.3.dist-info/WHEEL
parallelexec-0.0.3.dist-info/RECORD
