Metadata-Version: 2.1
Name: parallelexec
Version: 0.0.3
Summary: Module that provides decorators and methods to easily run multiple functions concurrently
License: MIT
Author: AshGw
Author-email: AshrefGw@proton.me
Requires-Python: >=3.9,<4.0
Classifier: License :: OSI Approved :: MIT License
Classifier: Programming Language :: Python :: 3
Classifier: Programming Language :: Python :: 3.9
Classifier: Programming Language :: Python :: 3.10
Classifier: Programming Language :: Python :: 3.11
Classifier: Programming Language :: Python :: 3.12
